m2m_postaviz/__init__.py
m2m_postaviz/__main__.py
m2m_postaviz/bin_exploration_module.py
m2m_postaviz/cli.py
m2m_postaviz/cpd_exploration_module.py
m2m_postaviz/data_struct.py
m2m_postaviz/data_utils.py
m2m_postaviz/lineage.py
m2m_postaviz/overview_module.py
m2m_postaviz/shiny_app.py
m2m_postaviz/shiny_module.py
m2m_postaviz/postaviz_test_data/padmet_dataframe_unit_test.tsv
m2m_postaviz/postaviz_test_data/table_test_postaviz.tar.gz
m2m_postaviz-0.1.1.dist-info/licenses/AUTHORS.rst
m2m_postaviz-0.1.1.dist-info/licenses/LICENSE
m2m_postaviz-0.1.1.dist-info/METADATA
m2m_postaviz-0.1.1.dist-info/WHEEL
m2m_postaviz-0.1.1.dist-info/entry_points.txt
m2m_postaviz-0.1.1.dist-info/top_level.txt
m2m_postaviz-0.1.1.dist-info/RECORD
