Metadata-Version: 2.4
Name: m2m-postaviz
Version: 0.1.1
Summary: Post-analysis and visualization of metage2metabo's results
Author-email: Pleiade team <leonard.brindel@inria.fr>
License: LGPL-3.0-or-later
Project-URL: Homepage, https://gitlab.inria.fr/postaviz/
Requires-Python: >=3.8
License-File: LICENSE
License-File: AUTHORS.rst
Requires-Dist: pandas
Requires-Dist: scipy
Requires-Dist: padmet
Requires-Dist: plotly
Requires-Dist: shiny
Requires-Dist: shinywidgets
Requires-Dist: scikit-bio
Requires-Dist: pyarrow
Requires-Dist: seaborn
Provides-Extra: cpu
Requires-Dist: polars; extra == "cpu"
Provides-Extra: lts-cpu
Requires-Dist: polars-lts-cpu; extra == "lts-cpu"
Dynamic: license-file
